lwa_readiness/__init__.py
lwa_readiness/asgi.py
aws_lwa_readiness_check-0.1.0.dist-info/LICENSE
aws_lwa_readiness_check-0.1.0.dist-info/METADATA
aws_lwa_readiness_check-0.1.0.dist-info/WHEEL
aws_lwa_readiness_check-0.1.0.dist-info/top_level.txt
aws_lwa_readiness_check-0.1.0.dist-info/RECORD
