Metadata-Version: 2.1
Name: aws-lwa-readiness-check
Version: 0.1.0
Summary: ASGI middleware for handling readiness check requests from AWS Lambda Web Adapter
Home-page: https://github.com/efficient-solutions/aws-lwa-readiness-check
Author: Efficient Solutions LLC
Author-email: contact@efficient.solutions
License: MIT
Keywords: AWS Lambda,AWS Lambda Web Adapter,ASGI
Classifier: Intended Audience :: Developers
Classifier: Natural Language :: English
Classifier: License :: OSI Approved :: MIT License
Classifier: Programming Language :: Python
Classifier: Programming Language :: Python :: 3
Classifier: Programming Language :: Python :: 3 :: Only
Classifier: Programming Language :: Python :: 3.10
Classifier: Programming Language :: Python :: 3.11
Classifier: Programming Language :: Python :: 3.12
Requires-Python: >= 3.10
License-File: LICENSE
